adobe/__init__.py
adobe/pdfservices/__init__.py
adobe/pdfservices/operation/__init__.py
adobe/pdfservices/operation/client_config.py
adobe/pdfservices/operation/execution_context.py
adobe/pdfservices/operation/operation.py
adobe/pdfservices/operation/auth/__init__.py
adobe/pdfservices/operation/auth/credentials.py
adobe/pdfservices/operation/auth/service_account_credentials.py
adobe/pdfservices/operation/exception/__init__.py
adobe/pdfservices/operation/exception/exceptions.py
adobe/pdfservices/operation/internal/__init__.py
adobe/pdfservices/operation/internal/exceptions.py
adobe/pdfservices/operation/internal/extension_media_type_mapping.py
adobe/pdfservices/operation/internal/internal_client_config.py
adobe/pdfservices/operation/internal/internal_execution_context.py
adobe/pdfservices/operation/internal/service_constants.py
adobe/pdfservices/operation/internal/api/__init__.py
adobe/pdfservices/operation/internal/api/cpf_api.py
adobe/pdfservices/operation/internal/api/dto/__init__.py
adobe/pdfservices/operation/internal/api/dto/document.py
adobe/pdfservices/operation/internal/api/dto/request/__init__.py
adobe/pdfservices/operation/internal/api/dto/request/extract_pdf_outputs.py
adobe/pdfservices/operation/internal/api/dto/request/extract_pdf_params.py
adobe/pdfservices/operation/internal/api/dto/request/platform/__init__.py
adobe/pdfservices/operation/internal/api/dto/request/platform/cpf_content_analyzer_req.py
adobe/pdfservices/operation/internal/api/dto/request/platform/cpf_params.py
adobe/pdfservices/operation/internal/api/dto/request/platform/engine.py
adobe/pdfservices/operation/internal/api/dto/request/platform/inline_params.py
adobe/pdfservices/operation/internal/api/dto/request/platform/inputs.py
adobe/pdfservices/operation/internal/api/dto/request/platform/outputs.py
adobe/pdfservices/operation/internal/api/dto/response/__init__.py
adobe/pdfservices/operation/internal/api/dto/response/extract_pdf_output_metadata.py
pdfservices_extract_sdk-1.0.0b1.dist-info/LICENSE.md
pdfservices_extract_sdk-1.0.0b1.dist-info/METADATA
pdfservices_extract_sdk-1.0.0b1.dist-info/WHEEL
pdfservices_extract_sdk-1.0.0b1.dist-info/top_level.txt
pdfservices_extract_sdk-1.0.0b1.dist-info/RECORD
