Metadata-Version: 2.1
Name: pdfservices-extract-sdk
Version: 1.0.0b1
Summary: Adobe Document Services Extract PDF API Client Library
Home-page: https://opensource.adobe.com/pdftools-sdk-docs/beta/extract/index.html#
Author: Adobe Document Services
Author-email: extractapi@adobe.com
License: Apache2
Platform: UNKNOWN
Classifier: Development Status :: 4 - Beta
Classifier: Intended Audience :: Developers
Classifier: Programming Language :: Python :: 3.6
Classifier: Programming Language :: Python :: 3.7
Classifier: Programming Language :: Python :: 3.8
Classifier: License :: OSI Approved :: Apache Software License
Classifier: Operating System :: OS Independent
Requires-Python: >=3.6
